sc_paginator/__init__.py
sc_paginator/sc_paginator.py
sc_paginator-0.0.6.dist-info/METADATA
sc_paginator-0.0.6.dist-info/WHEEL
sc_paginator-0.0.6.dist-info/licenses/LICENSE
sc_paginator-0.0.6.dist-info/RECORD
